{
    "category-v2.single.toJob": "vue-grp",
    "git.link": "https://github.com/echoedinvoker/vue_grp/blob/master/2-vue-admin/5-routes/memo.md",
    "course": "Vue 3, Vuetify and Nuxt.js: A Rapid Guide",
    "chapter": "2. Vue Admin",
    "section": "5. Routes",
    "video.length": 6,
    "time.comsuming": 55,
    "lecturer.name.first": "Antonio",
    "lecturer.name.last": "Papa",
    "register.time": "2023-03-17T08:22:34Z",
    "tag": [
      "vue","admin","router","page"
    ],
    "video.link": "https://www.udemy.com/course/vue-influencer/learn/lecture/26068672#content",
    "description": "Create some page components."
  }

